depcheckr/__init__.py
depcheckr/__main__.py
depcheckr/cli.py
depcheckr/helpers.py
depcheckr-0.1.3.dist-info/METADATA
depcheckr-0.1.3.dist-info/WHEEL
depcheckr-0.1.3.dist-info/entry_points.txt
depcheckr-0.1.3.dist-info/licenses/LICENSE
depcheckr-0.1.3.dist-info/RECORD
