Metadata-Version: 2.4
Name: depcheckr
Version: 0.1.3
Summary: Effortlessly inspect and upgrade dependencies in your pyproject.toml
Project-URL: homepage, https://github.com/ashenlabs/depcheckr
Author-email: Patrick Mazulo <mazulo@ashenlabs.dev>
License: MIT
License-File: LICENSE
Keywords: cli,dependencies,pyproject,version-checker
Classifier: Development Status :: 3 - Alpha
Classifier: Intended Audience :: Developers
Classifier: License :: OSI Approved :: MIT License
Classifier: Programming Language :: Python :: 3.13
Classifier: Topic :: Software Development :: Libraries :: Python Modules
Requires-Python: >=3.12
Requires-Dist: httpx
Requires-Dist: packaging>=25.0
Requires-Dist: rich>=13.0.0
Requires-Dist: tomli-w
Requires-Dist: typer>=0.16.0
